MANIFEST.in
requirements-test.txt
requirements.txt
setup.py
stdeb.cfg
upaas
debian/changelog
debian/compat
debian/control
debian/python-upaas-client.preinst
debian/rules
debian/source/format
upaas_client/__init__.py
upaas_client/config.py
upaas_client/main.py
upaas_client/return_codes.py
upaas_client.egg-info/PKG-INFO
upaas_client.egg-info/SOURCES.txt
upaas_client.egg-info/dependency_links.txt
upaas_client.egg-info/requires.txt
upaas_client.egg-info/top_level.txt
upaas_client/applications/__init__.py
upaas_client/applications/build.py
upaas_client/applications/edit.py
upaas_client/applications/list.py
upaas_client/applications/register.py
upaas_client/applications/show.py
upaas_client/applications/start.py
upaas_client/applications/stop.py
upaas_client/applications/update.py