Metadata-Version: 1.1
Name: upaas-client
Version: 0.2.1a
Summary: uPaaS CLI client
Home-page: https://github.com/prymitive/upaas-client
Author: Łukasz Mierzwa
Author-email: l.mierzwa@gmail.com
License: GPLv3
Platform: Linux
Classifier: License :: OSI Approved :: GNU General Public License v3 (GPLv3)
Classifier: Intended Audience :: System Administrators
Classifier: Programming Language :: Python
